autolabel/__init__.py
autolabel/__main__.py
autolabel/confidence.py
autolabel/labeler.py
autolabel/schema.py
autolabel/utils.py
autolabel/cache/__init__.py
autolabel/cache/base.py
autolabel/cache/redis_cache.py
autolabel/cache/sqlalchemy_generation_cache.py
autolabel/cache/sqlalchemy_transform_cache.py
autolabel/cli/__init__.py
autolabel/cli/config.py
autolabel/cli/main.py
autolabel/cli/template.py
autolabel/configs/__init__.py
autolabel/configs/base.py
autolabel/configs/config.py
autolabel/configs/schema.py
autolabel/data_models/__init__.py
autolabel/data_models/annotation.py
autolabel/data_models/base.py
autolabel/data_models/dataset.py
autolabel/data_models/generation_cache.py
autolabel/data_models/task.py
autolabel/data_models/task_run.py
autolabel/data_models/transform_cache.py
autolabel/database/__init__.py
autolabel/database/engine.py
autolabel/database/state_manager.py
autolabel/dataset/__init__.py
autolabel/dataset/dataset.py
autolabel/dataset/validation.py
autolabel/few_shot/__init__.py
autolabel/few_shot/fixed_example_selector.py
autolabel/few_shot/label_diversity_example_selector.py
autolabel/few_shot/label_selector.py
autolabel/few_shot/vector_store.py
autolabel/metrics/__init__.py
autolabel/metrics/accuracy.py
autolabel/metrics/auroc.py
autolabel/metrics/base.py
autolabel/metrics/classification_report.py
autolabel/metrics/completion_rate.py
autolabel/metrics/f1.py
autolabel/metrics/support.py
autolabel/models/__init__.py
autolabel/models/anthropic.py
autolabel/models/base.py
autolabel/models/cohere.py
autolabel/models/hf_pipeline.py
autolabel/models/openai.py
autolabel/models/palm.py
autolabel/models/refuel.py
autolabel/tasks/__init__.py
autolabel/tasks/attribute_extraction.py
autolabel/tasks/base.py
autolabel/tasks/classification.py
autolabel/tasks/entity_matching.py
autolabel/tasks/multilabel_classification.py
autolabel/tasks/named_entity_recognition.py
autolabel/tasks/question_answering.py
autolabel/tasks/utils.py
autolabel/transforms/__init__.py
refuel_autolabel-0.0.16.dist-info/LICENSE
refuel_autolabel-0.0.16.dist-info/METADATA
refuel_autolabel-0.0.16.dist-info/WHEEL
refuel_autolabel-0.0.16.dist-info/entry_points.txt
refuel_autolabel-0.0.16.dist-info/top_level.txt
refuel_autolabel-0.0.16.dist-info/RECORD
