Metadata-Version: 2.1
Name: refuel-autolabel
Version: 0.0.16
Summary: Label, clean and enrich text datasets with LLMs
Author-email: "Refuel.ai" <support@refuel.ai>
License: MIT License
Project-URL: Homepage, https://github.com/refuel-ai/autolabel
Classifier: Development Status :: 4 - Beta
Classifier: License :: OSI Approved :: MIT License
Classifier: Programming Language :: Python
Classifier: Programming Language :: Python :: 3
Classifier: Topic :: Software Development :: Libraries :: Python Modules
Classifier: Topic :: Scientific/Engineering :: Artificial Intelligence
Requires-Python: >=3.6
License-File: LICENSE
Requires-Dist: loguru >=0.5.0
Requires-Dist: numpy >=1.23.0
Requires-Dist: requests >=2.27.0
Requires-Dist: datasets >=2.7.0
Requires-Dist: langchain ==0.0.226
Requires-Dist: nervaluate >=0.1.8
Requires-Dist: pandas >=1.3.0
Requires-Dist: scikit-learn >=1.0.0
Requires-Dist: tenacity >=8.2.2
Requires-Dist: SQLAlchemy >=2.0.19
Requires-Dist: regex >=2023.6.3
Requires-Dist: rich >=13.3.5
Requires-Dist: scipy >=1.10.1
Requires-Dist: pydantic >=1.10.9
Requires-Dist: torch >=1.10.0
Requires-Dist: matplotlib >=3.5.0
Requires-Dist: wget >=3.2
Requires-Dist: ipywidgets ==8.0.6
Requires-Dist: jsonschema >=4.17.3
Requires-Dist: tabulate >=0.9.0
Requires-Dist: typer[all] >=0.9.0
Requires-Dist: simple-term-menu >=1.6.1
Provides-Extra: all
Requires-Dist: black ; extra == 'all'
Requires-Dist: bumpver ; extra == 'all'
Requires-Dist: pip-tools ; extra == 'all'
Requires-Dist: pytest ; extra == 'all'
Requires-Dist: pytest-asyncio ; extra == 'all'
Requires-Dist: pytest-mock ; extra == 'all'
Requires-Dist: pre-commit ; extra == 'all'
Requires-Dist: openai >=0.27.4 ; extra == 'all'
Requires-Dist: tiktoken >=0.3.3 ; extra == 'all'
Requires-Dist: anthropic ==0.3.0 ; extra == 'all'
Requires-Dist: transformers >=4.25.0 ; extra == 'all'
Requires-Dist: google-cloud-aiplatform >=1.25.0 ; extra == 'all'
Requires-Dist: google-search-results >=2.4.2 ; extra == 'all'
Requires-Dist: cohere >=4.11.2 ; extra == 'all'
Requires-Dist: redis >=3.5.3 ; extra == 'all'
Requires-Dist: sentence-transformers ; extra == 'all'
Requires-Dist: pdfplumber >=0.10.2 ; extra == 'all'
Requires-Dist: pdf2image >=1.16.3 ; extra == 'all'
Requires-Dist: pytesseract >=0.3.10 ; extra == 'all'
Requires-Dist: beautifulsoup4 >=4.12.2 ; extra == 'all'
Requires-Dist: httpx ; extra == 'all'
Requires-Dist: fake-useragent ; extra == 'all'
Requires-Dist: pillow >=9.5.0 ; extra == 'all'
Provides-Extra: anthropic
Requires-Dist: anthropic ==0.3.0 ; extra == 'anthropic'
Provides-Extra: cohere
Requires-Dist: cohere >=4.11.2 ; extra == 'cohere'
Provides-Extra: dev
Requires-Dist: black ; extra == 'dev'
Requires-Dist: bumpver ; extra == 'dev'
Requires-Dist: mkdocs ; extra == 'dev'
Requires-Dist: mkdocs-autorefs ; extra == 'dev'
Requires-Dist: mkdocs-jupyter ; extra == 'dev'
Requires-Dist: mkdocs-material ; extra == 'dev'
Requires-Dist: mkdocs-material-extensions ; extra == 'dev'
Requires-Dist: mkdocs-table-reader-plugin ; extra == 'dev'
Requires-Dist: mkdocstrings ; extra == 'dev'
Requires-Dist: mkdocstrings-python ; extra == 'dev'
Requires-Dist: pip-tools ; extra == 'dev'
Requires-Dist: pytest ; extra == 'dev'
Requires-Dist: pytest-asyncio ; extra == 'dev'
Requires-Dist: pytest-mock ; extra == 'dev'
Requires-Dist: pre-commit ; extra == 'dev'
Provides-Extra: google
Requires-Dist: google-cloud-aiplatform >=1.25.0 ; extra == 'google'
Provides-Extra: huggingface
Requires-Dist: transformers >=4.25.0 ; extra == 'huggingface'
Requires-Dist: sentence-transformers ; extra == 'huggingface'
Provides-Extra: openai
Requires-Dist: openai >=0.27.4 ; extra == 'openai'
Requires-Dist: tiktoken >=0.3.3 ; extra == 'openai'
